<?xml version="1.0"?>
<!DOCTYPE hibernate-mapping PUBLIC 
	"-//Hibernate/Hibernate Mapping DTD 3.0//EN"
	"http://www.hibernate.org/dtd/hibernate-mapping-3.0.dtd">

<!-- Generated 2017-12-15 9:35:55 by Hibernate Tools 5.2.6.Final -->
<hibernate-mapping>

	<class name="com.qhit.lh.g4.wf.t3.bean.TUserinfo" table="t_userinfo"
		optimistic-lock="version">

		<id name="userId" type="int">

			<column name="userId" />
			<generator class="assigned" />
		</id>




		<property name="userName" type="string">
			<column name="userName" length="30" not-null="true" />
		</property>

		<property name="userPwd" type="string">
			<column name="userPwd" length="30" not-null="true" />
		</property>
		<one-to-one name="emp" class="com.qhit.lh.g4.perfact.t3.bean.TEmp" cascade="all"/>

	</class>

</hibernate-mapping>